[
    {
        "id":  "counting",
        "name":  "Counting",
        "file":  "counting.json"
    },
    {
        "id":  "greetings",
        "name":  "Greetings",
        "file":  "greetings.json"
    },
    {
        "id":  "colors",
        "name":  "Colors",
        "file":  "colors.json"
    },
    {
        "id":  "days",
        "name":  "Days of the Week",
        "file":  "days.json"
    },
    {
        "id":  "months",
        "name":  "Months",
        "file":  "months.json"
    },
    {
        "id":  "seasons",
        "name":  "Seasons",
        "file":  "seasons.json"
    },
    {
        "id":  "weather",
        "name":  "Weather",
        "file":  "weather.json"
    },
    {
        "id":  "time",
        "name":  "Time Expressions",
        "file":  "time.json"
    },
    {
        "id":  "basic-verbs",
        "name":  "Basic Verbs",
        "file":  "basic-verbs.json"
    },
    {
        "id":  "basic-adjectives",
        "name":  "Basic Adjectives",
        "file":  "basic-adjectives.json"
    },
    {
        "id":  "question-words",
        "name":  "Question Words",
        "file":  "question-words.json"
    },
    {
        "id":  "prepositions",
        "name":  "Prepositions",
        "file":  "prepositions.json"
    },
    {
        "id":  "connectors",
        "name":  "Connectors",
        "file":  "connectors.json"
    },
    {
        "id":  "opposites",
        "name":  "Opposites",
        "file":  "opposites.json"
    },
    {
        "id":  "calendar",
        "name":  "Calendar Terms",
        "file":  "calendar.json"
    },
    {
        "id":  "clock",
        "name":  "Clock and Time",
        "file":  "clock.json"
    },
    {
        "id":  "ordinal-numbers",
        "name":  "Ordinal Numbers",
        "file":  "ordinal-numbers.json"
    },
    {
        "id":  "classroom",
        "name":  "Classroom",
        "file":  "classroom.json"
    },
    {
        "id":  "school-subjects",
        "name":  "School Subjects",
        "file":  "school-subjects.json"
    },
    {
        "id":  "stationery",
        "name":  "Stationery",
        "file":  "stationery.json"
    },
    {
        "id":  "exams",
        "name":  "Exams",
        "file":  "exams.json"
    },
    {
        "id":  "university",
        "name":  "University",
        "file":  "university.json"
    },
    {
        "id":  "books",
        "name":  "Books",
        "file":  "books.json"
    },
    {
        "id":  "library",
        "name":  "Library",
        "file":  "library.json"
    },
    {
        "id":  "food",
        "name":  "Food",
        "file":  "food.json"
    },
    {
        "id":  "drinks",
        "name":  "Drinks",
        "file":  "drinks.json"
    },
    {
        "id":  "fruits",
        "name":  "Fruits",
        "file":  "fruits.json"
    },
    {
        "id":  "vegetables",
        "name":  "Vegetables",
        "file":  "vegetables.json"
    },
    {
        "id":  "meals",
        "name":  "Meals",
        "file":  "meals.json"
    },
    {
        "id":  "kitchen",
        "name":  "Kitchen",
        "file":  "kitchen.json"
    },
    {
        "id":  "restaurant",
        "name":  "Restaurant",
        "file":  "restaurant.json"
    },
    {
        "id":  "breakfast",
        "name":  "Breakfast",
        "file":  "breakfast.json"
    },
    {
        "id":  "lunch",
        "name":  "Lunch",
        "file":  "lunch.json"
    },
    {
        "id":  "dinner",
        "name":  "Dinner",
        "file":  "dinner.json"
    },
    {
        "id":  "snacks",
        "name":  "Snacks",
        "file":  "snacks.json"
    },
    {
        "id":  "spices",
        "name":  "Spices",
        "file":  "spices.json"
    },
    {
        "id":  "cooking-verbs",
        "name":  "Cooking Verbs",
        "file":  "cooking-verbs.json"
    },
    {
        "id":  "baking",
        "name":  "Baking",
        "file":  "baking.json"
    },
    {
        "id":  "relatives",
        "name":  "Relatives",
        "file":  "relatives.json"
    },
    {
        "id":  "home",
        "name":  "Home",
        "file":  "home.json"
    },
    {
        "id":  "rooms",
        "name":  "Rooms",
        "file":  "rooms.json"
    },
    {
        "id":  "furniture",
        "name":  "Furniture",
        "file":  "furniture.json"
    },
    {
        "id":  "household-items",
        "name":  "Household Items",
        "file":  "household-items.json"
    },
    {
        "id":  "house-chores",
        "name":  "House Chores",
        "file":  "house-chores.json"
    },
    {
        "id":  "daily-routine",
        "name":  "Daily Routine",
        "file":  "daily-routine.json"
    },
    {
        "id":  "bathroom",
        "name":  "Bathroom",
        "file":  "bathroom.json"
    },
    {
        "id":  "bedroom",
        "name":  "Bedroom",
        "file":  "bedroom.json"
    },
    {
        "id":  "living-room",
        "name":  "Living Room",
        "file":  "living-room.json"
    },
    {
        "id":  "clothing",
        "name":  "Clothing",
        "file":  "clothing.json"
    },
    {
        "id":  "accessories",
        "name":  "Accessories",
        "file":  "accessories.json"
    },
    {
        "id":  "shoes",
        "name":  "Shoes",
        "file":  "shoes.json"
    },
    {
        "id":  "body",
        "name":  "Body",
        "file":  "body.json"
    },
    {
        "id":  "face",
        "name":  "Face",
        "file":  "face.json"
    },
    {
        "id":  "health",
        "name":  "Health",
        "file":  "health.json"
    },
    {
        "id":  "doctor",
        "name":  "Doctor and Pharmacy",
        "file":  "doctor.json"
    },
    {
        "id":  "emotions",
        "name":  "Emotions",
        "file":  "emotions.json"
    },
    {
        "id":  "personality",
        "name":  "Personality",
        "file":  "personality.json"
    },
    {
        "id":  "jobs",
        "name":  "Jobs",
        "file":  "jobs.json"
    },
    {
        "id":  "office",
        "name":  "Office",
        "file":  "office.json"
    },
    {
        "id":  "hobbies",
        "name":  "Hobbies",
        "file":  "hobbies.json"
    },
    {
        "id":  "sports",
        "name":  "Sports",
        "file":  "sports.json"
    },
    {
        "id":  "music",
        "name":  "Music",
        "file":  "music.json"
    },
    {
        "id":  "art",
        "name":  "Art",
        "file":  "art.json"
    },
    {
        "id":  "cinema",
        "name":  "Cinema",
        "file":  "cinema.json"
    },
    {
        "id":  "reading",
        "name":  "Reading",
        "file":  "reading.json"
    },
    {
        "id":  "writing",
        "name":  "Writing",
        "file":  "writing.json"
    },
    {
        "id":  "photography",
        "name":  "Photography",
        "file":  "photography.json"
    },
    {
        "id":  "dance",
        "name":  "Dance",
        "file":  "dance.json"
    },
    {
        "id":  "travel",
        "name":  "Travel",
        "file":  "travel.json"
    },
    {
        "id":  "transport",
        "name":  "Transport",
        "file":  "transport.json"
    },
    {
        "id":  "directions",
        "name":  "Directions",
        "file":  "directions.json"
    },
    {
        "id":  "city",
        "name":  "City",
        "file":  "city.json"
    },
    {
        "id":  "countryside",
        "name":  "Countryside",
        "file":  "countryside.json"
    },
    {
        "id":  "airport",
        "name":  "Airport",
        "file":  "airport.json"
    },
    {
        "id":  "hotel",
        "name":  "Hotel",
        "file":  "hotel.json"
    },
    {
        "id":  "shopping",
        "name":  "Shopping",
        "file":  "shopping.json"
    },
    {
        "id":  "money",
        "name":  "Money",
        "file":  "money.json"
    },
    {
        "id":  "banking",
        "name":  "Banking",
        "file":  "banking.json"
    },
    {
        "id":  "post-office",
        "name":  "Post Office",
        "file":  "post-office.json"
    },
    {
        "id":  "police",
        "name":  "Police",
        "file":  "police.json"
    },
    {
        "id":  "emergency",
        "name":  "Emergency",
        "file":  "emergency.json"
    },
    {
        "id":  "nature",
        "name":  "Nature",
        "file":  "nature.json"
    },
    {
        "id":  "animals",
        "name":  "Animals",
        "file":  "animals.json"
    },
    {
        "id":  "pets",
        "name":  "Pets",
        "file":  "pets.json"
    },
    {
        "id":  "farm-animals",
        "name":  "Farm Animals",
        "file":  "farm-animals.json"
    },
    {
        "id":  "wild-animals",
        "name":  "Wild Animals",
        "file":  "wild-animals.json"
    },
    {
        "id":  "insects",
        "name":  "Insects",
        "file":  "insects.json"
    },
    {
        "id":  "birds",
        "name":  "Birds",
        "file":  "birds.json"
    },
    {
        "id":  "sea",
        "name":  "Sea",
        "file":  "sea.json"
    },
    {
        "id":  "beach",
        "name":  "Beach",
        "file":  "beach.json"
    },
    {
        "id":  "mountain",
        "name":  "Mountain",
        "file":  "mountain.json"
    },
    {
        "id":  "camping",
        "name":  "Camping",
        "file":  "camping.json"
    },
    {
        "id":  "environment",
        "name":  "Environment",
        "file":  "environment.json"
    },
    {
        "id":  "recycling",
        "name":  "Recycling",
        "file":  "recycling.json"
    },
    {
        "id":  "energy",
        "name":  "Energy",
        "file":  "energy.json"
    },
    {
        "id":  "gardening",
        "name":  "Gardening",
        "file":  "gardening.json"
    },
    {
        "id":  "space",
        "name":  "Space",
        "file":  "space.json"
    },
    {
        "id":  "technology",
        "name":  "Technology",
        "file":  "technology.json"
    },
    {
        "id":  "internet",
        "name":  "Internet",
        "file":  "internet.json"
    },
    {
        "id":  "computer",
        "name":  "Computer",
        "file":  "computer.json"
    }
]
